nameko_bayeux_client/__init__.py
nameko_bayeux_client/channels.py
nameko_bayeux_client/client.py
nameko_bayeux_client/constants.py
nameko_bayeux_client/exceptions.py
nameko_bayeux_client-1.0.0.dist-info/DESCRIPTION.rst
nameko_bayeux_client-1.0.0.dist-info/METADATA
nameko_bayeux_client-1.0.0.dist-info/RECORD
nameko_bayeux_client-1.0.0.dist-info/WHEEL
nameko_bayeux_client-1.0.0.dist-info/metadata.json
nameko_bayeux_client-1.0.0.dist-info/top_level.txt
nameko_bayeux_client-1.0.0.dist-info/zip-safe
