Metadata-Version: 2.0
Name: nameko-bayeux-client
Version: 1.0.0
Summary: Nameko extension with a Cometd client implementing Bayeux protocol
Home-page: http://github.com/iky/nameko-bayeux-client
Author: Student.com
Author-email: UNKNOWN
License: Apache License, Version 2.0
Platform: UNKNOWN
Classifier: Programming Language :: Python
Classifier: Operating System :: MacOS :: MacOS X
Classifier: Operating System :: POSIX
Classifier: Programming Language :: Python :: 3.4
Classifier: Programming Language :: Python :: 3.5
Classifier: Programming Language :: Python :: 3.6
Classifier: Topic :: Internet
Classifier: Topic :: Software Development :: Libraries :: Python Modules
Classifier: Intended Audience :: Developers
Requires-Dist: nameko (>=2.5.1)
Provides-Extra: dev
Requires-Dist: coverage (==4.3.4); extra == 'dev'
Requires-Dist: flake8 (==3.2.1); extra == 'dev'
Requires-Dist: pylint (==1.8.2); extra == 'dev'
Requires-Dist: pytest (==3.0.6); extra == 'dev'
Requires-Dist: requests-mock (==1.3.0); extra == 'dev'
